{
  "users": [],
  "nodes": [
    {
      "nodename": "daspidercave",
      "ip": "127.0.0.1:8082",
      "nodestatus": {
        "kind": "Enabled"
      },
      "nodetype": {
        "kind": "Custom"
      }
    },
    {
      "nodename": "test",
      "ip": "127.0.0.1:8083",
      "nodestatus": {
        "kind": "Enabled"
      },
      "nodetype": {
        "kind": "Main"
      }
    }
  ],
  "servers": [
    {
      "servername": "create_server",
      "provider": "",
      "providertype": "custom",
      "location": ""
    }
  ],
  "buttons": [
    {
      "name": "Filebrowser",
      "link": "",
      "type": "default"
    },
    {
      "name": "Statistics",
      "link": "",
      "type": "default"
    },
    {
      "name": "Workflows",
      "link": "",
      "type": "default"
    },
    {
      "name": "Intergrations",
      "link": "",
      "type": "default"
    },
    {
      "name": "Backups",
      "link": "",
      "type": "default"
    },
    {
      "name": "Settings",
      "link": "",
      "type": "default"
    }
  ],
  "toggled_buttons": [
    {
      "name": "Filebrowser",
      "link": "",
      "type": "default"
    },
    {
      "name": "Statistics",
      "link": "",
      "type": "default"
    },
    {
      "name": "Workflows",
      "link": "",
      "type": "default"
    },
    {
      "name": "Intergrations",
      "link": "",
      "type": "default"
    },
    {
      "name": "Backups",
      "link": "",
      "type": "default"
    },
    {
      "name": "Settings",
      "link": "",
      "type": "default"
    }
  ],
  "settings": {
    "toggled_default_buttons": false
  }
}